gimpact.cpython-313-darwin.so
gimpact-1.0.2.dist-info/RECORD
gimpact-1.0.2.dist-info/WHEEL
gimpact-1.0.2.dist-info/top_level.txt
gimpact-1.0.2.dist-info/METADATA
gimpact-1.0.2.dist-info/licenses/LICENSE
