Metadata-Version: 2.4
Name: gimpact
Version: 1.0.2
Summary: An unofficial python extension for the GImpact collision library
Home-page: https://github.com/StephenNneji
Author: Stephen Nneji
Author-email: Stephen Nneji <steve.nneji@gmail.com>
License-Expression: BSD-3-Clause
Keywords: GImpact,Trimesh,Collision detection,Cython
Classifier: Development Status :: 5 - Production/Stable
Classifier: Intended Audience :: Developers
Classifier: Intended Audience :: Science/Research
Classifier: Topic :: Games/Entertainment :: Simulation
Classifier: Topic :: Scientific/Engineering :: Physics
Classifier: Operating System :: Microsoft :: Windows
Classifier: Operating System :: POSIX
Classifier: Programming Language :: Python :: 3.11
Classifier: Programming Language :: Python :: 3.12
Classifier: Programming Language :: Python :: 3.13
Classifier: Programming Language :: Python :: Implementation :: CPython
Classifier: Programming Language :: Cython
Requires-Python: >=3.6
License-File: LICENSE
Requires-Dist: numpy>=1.18.5
Dynamic: author
Dynamic: home-page
Dynamic: license-file
